llyr/__init__.py
llyr/_utils.py
llyr/base.py
llyr/calc/__init__.py
llyr/calc/anim.py
llyr/calc/disp.py
llyr/calc/fft.py
llyr/calc/fft_tb.py
llyr/calc/fminmax.py
llyr/calc/modes.py
llyr/calc/peaks.py
llyr/calc/sk_number.py
llyr/plot/__init__.py
llyr/plot/anim.py
llyr/plot/cross_section.py
llyr/plot/fft_tb.py
llyr/plot/imshow.py
llyr/plot/modes.py
llyr/plot/p3d.py
llyr/plot/report.py
llyr/plot/sin_anim.py
llyr/plot/snapshot.py
llyr/plot/snapshot_png.py
llyr-0.2.2.dist-info/LICENSE
llyr-0.2.2.dist-info/METADATA
llyr-0.2.2.dist-info/WHEEL
llyr-0.2.2.dist-info/top_level.txt
llyr-0.2.2.dist-info/RECORD
