Metadata-Version: 2.1
Name: llyr
Version: 0.2.2
Summary: micromagnetic post processing library
Home-page: https://github.com/MathieuMoalic/llyr
Author: Mathieu Moalic
Author-email: matmoa@pm.me
License: GPL-3.0
Platform: any
Requires-Dist: PeakUtils (>=1.3.3)
Requires-Dist: appdirs (>=1.4.4)
Requires-Dist: cmocean (>=2.0)
Requires-Dist: dask (>=2021.4.0)
Requires-Dist: distributed (>=2021.4.0)
Requires-Dist: k3d (>=2.11.0)
Requires-Dist: matplotlib (>=3.4.1)
Requires-Dist: numpy (>=1.20.2)
Requires-Dist: psutil (>=5.8.0)
Requires-Dist: tqdm (>=4.60.0)
Requires-Dist: zarr (>=2.10.2)
